pyhakuna/__init__.py
pyhakuna/hakuna/__init__.py
pyhakuna/hakuna/auth.py
pyhakuna/hakuna/request.py
pyhakuna/hakuna/global_/__init__.py
pyhakuna/hakuna/global_/absence_types.py
pyhakuna/hakuna/global_/company.py
pyhakuna/hakuna/global_/projects.py
pyhakuna/hakuna/global_/tasks.py
pyhakuna/hakuna/organization/__init__.py
pyhakuna/hakuna/personal/__init__.py
pyhakuna/hakuna/personal/absences.py
pyhakuna/hakuna/personal/overview.py
pyhakuna/hakuna/personal/time_entries.py
pyhakuna/hakuna/personal/timer.py
pyhakuna/hakuna/personal/users.py
pyhakuna-0.0.3.dist-info/LICENSE
pyhakuna-0.0.3.dist-info/METADATA
pyhakuna-0.0.3.dist-info/WHEEL
pyhakuna-0.0.3.dist-info/top_level.txt
pyhakuna-0.0.3.dist-info/RECORD
