Metadata-Version: 2.1
Name: pyhakuna
Version: 0.0.3
Summary: A Python library to access the API of hakuna.ch
Home-page: https://github.com/cimnine/hakunaStreamDeck
Author: Christian Mäder
Author-email: pyhakuna@cimnine.ch
License: BSD 3-Clause License
Platform: UNKNOWN
Classifier: Development Status :: 3 - Alpha
Classifier: Intended Audience :: Developers
Classifier: License :: OSI Approved :: MIT License
Classifier: Natural Language :: English
Classifier: Operating System :: MacOS :: MacOS X
Classifier: Operating System :: Microsoft :: Windows
Classifier: Operating System :: POSIX
Classifier: Programming Language :: Python :: 3
Classifier: Topic :: Software Development
Requires-Python: >=3.7
License-File: LICENSE
Requires-Dist: requests (>=2.27.1)
